{
  "type": "GROUP",
"name": "Global Information",
"path": "",
"pathFormatted": "group_missing-name-b06d1",
"stats": {
    "name": "Global Information",
    "numberOfRequests": {
        "total": 7629,
        "ok": 4187,
        "ko": 3442
    },
    "minResponseTime": {
        "total": 0,
        "ok": 3,
        "ko": 0
    },
    "maxResponseTime": {
        "total": 59923,
        "ok": 59923,
        "ko": 50283
    },
    "meanResponseTime": {
        "total": 11054,
        "ok": 17303,
        "ko": 3453
    },
    "standardDeviation": {
        "total": 14766,
        "ok": 16870,
        "ko": 5638
    },
    "percentiles1": {
        "total": 5646,
        "ok": 9843,
        "ko": 2709
    },
    "percentiles2": {
        "total": 12597,
        "ok": 19908,
        "ko": 4420
    },
    "percentiles3": {
        "total": 50619,
        "ok": 52881,
        "ko": 6920
    },
    "percentiles4": {
        "total": 55957,
        "ok": 57317,
        "ko": 47906
    },
    "group1": {
        "name": "t < 500 ms",
        "count": 227,
        "percentage": 3
    },
    "group2": {
        "name": "500 ms < t < 1000 ms",
        "count": 23,
        "percentage": 0
    },
    "group3": {
        "name": "t > 1000 ms",
        "count": 3937,
        "percentage": 52
    },
    "group4": {
        "name": "failed",
        "count": 3442,
        "percentage": 45
    },
    "meanNumberOfRequestsPerSecond": {
        "total": 41.46195652173913,
        "ok": 22.755434782608695,
        "ko": 18.706521739130434
    }
},
"contents": {
"req_post-http---loc-0765e": {
        "type": "REQUEST",
        "name": "POST http://localhost:3001/api/front/v1/signup",
"path": "POST http://localhost:3001/api/front/v1/signup",
"pathFormatted": "req_post-http---loc-0765e",
"stats": {
    "name": "POST http://localhost:3001/api/front/v1/signup",
    "numberOfRequests": {
        "total": 1000,
        "ok": 608,
        "ko": 392
    },
    "minResponseTime": {
        "total": 0,
        "ok": 338,
        "ko": 0
    },
    "maxResponseTime": {
        "total": 59923,
        "ok": 59923,
        "ko": 0
    },
    "meanResponseTime": {
        "total": 20084,
        "ok": 33032,
        "ko": 0
    },
    "standardDeviation": {
        "total": 21985,
        "ok": 19164,
        "ko": 0
    },
    "percentiles1": {
        "total": 7256,
        "ok": 38259,
        "ko": 0
    },
    "percentiles2": {
        "total": 41607,
        "ok": 48578,
        "ko": 0
    },
    "percentiles3": {
        "total": 56413,
        "ok": 57951,
        "ko": 0
    },
    "percentiles4": {
        "total": 59414,
        "ok": 59527,
        "ko": 0
    },
    "group1": {
        "name": "t < 500 ms",
        "count": 4,
        "percentage": 0
    },
    "group2": {
        "name": "500 ms < t < 1000 ms",
        "count": 4,
        "percentage": 0
    },
    "group3": {
        "name": "t > 1000 ms",
        "count": 600,
        "percentage": 60
    },
    "group4": {
        "name": "failed",
        "count": 392,
        "percentage": 39
    },
    "meanNumberOfRequestsPerSecond": {
        "total": 5.434782608695652,
        "ok": 3.3043478260869565,
        "ko": 2.130434782608696
    }
}
    },"req_get-http---loca-25782": {
        "type": "REQUEST",
        "name": "GET http://localhost:3001/api/front/v1/activate-account",
"path": "GET http://localhost:3001/api/front/v1/activate-account",
"pathFormatted": "req_get-http---loca-25782",
"stats": {
    "name": "GET http://localhost:3001/api/front/v1/activate-account",
    "numberOfRequests": {
        "total": 608,
        "ok": 608,
        "ko": 0
    },
    "minResponseTime": {
        "total": 3,
        "ok": 3,
        "ko": 0
    },
    "maxResponseTime": {
        "total": 7132,
        "ok": 7132,
        "ko": 0
    },
    "meanResponseTime": {
        "total": 3733,
        "ok": 3733,
        "ko": 0
    },
    "standardDeviation": {
        "total": 2504,
        "ok": 2504,
        "ko": 0
    },
    "percentiles1": {
        "total": 4919,
        "ok": 4919,
        "ko": 0
    },
    "percentiles2": {
        "total": 5330,
        "ok": 5330,
        "ko": 0
    },
    "percentiles3": {
        "total": 6715,
        "ok": 6715,
        "ko": 0
    },
    "percentiles4": {
        "total": 7065,
        "ok": 7065,
        "ko": 0
    },
    "group1": {
        "name": "t < 500 ms",
        "count": 182,
        "percentage": 30
    },
    "group2": {
        "name": "500 ms < t < 1000 ms",
        "count": 0,
        "percentage": 0
    },
    "group3": {
        "name": "t > 1000 ms",
        "count": 426,
        "percentage": 70
    },
    "group4": {
        "name": "failed",
        "count": 0,
        "percentage": 0
    },
    "meanNumberOfRequestsPerSecond": {
        "total": 3.3043478260869565,
        "ok": 3.3043478260869565,
        "ko": 0
    }
}
    },"req_post-http---loc-f31e6": {
        "type": "REQUEST",
        "name": "POST http://localhost:3001/api/front/v1/login",
"path": "POST http://localhost:3001/api/front/v1/login",
"pathFormatted": "req_post-http---loc-f31e6",
"stats": {
    "name": "POST http://localhost:3001/api/front/v1/login",
    "numberOfRequests": {
        "total": 1000,
        "ok": 608,
        "ko": 392
    },
    "minResponseTime": {
        "total": 3174,
        "ok": 11563,
        "ko": 3174
    },
    "maxResponseTime": {
        "total": 56589,
        "ok": 56589,
        "ko": 50283
    },
    "meanResponseTime": {
        "total": 27890,
        "ok": 40208,
        "ko": 8785
    },
    "standardDeviation": {
        "total": 22485,
        "ok": 17716,
        "ko": 14233
    },
    "percentiles1": {
        "total": 14140,
        "ok": 50043,
        "ko": 4120
    },
    "percentiles2": {
        "total": 50697,
        "ok": 52418,
        "ko": 4145
    },
    "percentiles3": {
        "total": 54817,
        "ok": 55774,
        "ko": 48871
    },
    "percentiles4": {
        "total": 56188,
        "ok": 56340,
        "ko": 50042
    },
    "group1": {
        "name": "t < 500 ms",
        "count": 0,
        "percentage": 0
    },
    "group2": {
        "name": "500 ms < t < 1000 ms",
        "count": 0,
        "percentage": 0
    },
    "group3": {
        "name": "t > 1000 ms",
        "count": 608,
        "percentage": 61
    },
    "group4": {
        "name": "failed",
        "count": 392,
        "percentage": 39
    },
    "meanNumberOfRequestsPerSecond": {
        "total": 5.434782608695652,
        "ok": 3.3043478260869565,
        "ko": 2.130434782608696
    }
}
    },"req_get--api-v1-fro-36d2c": {
        "type": "REQUEST",
        "name": "GET /api/v1/front/trading/market/buy",
"path": "GET /api/v1/front/trading/market/buy",
"pathFormatted": "req_get--api-v1-fro-36d2c",
"stats": {
    "name": "GET /api/v1/front/trading/market/buy",
    "numberOfRequests": {
        "total": 1288,
        "ok": 0,
        "ko": 1288
    },
    "minResponseTime": {
        "total": 7,
        "ok": 0,
        "ko": 7
    },
    "maxResponseTime": {
        "total": 7354,
        "ok": 0,
        "ko": 7354
    },
    "meanResponseTime": {
        "total": 3390,
        "ok": 0,
        "ko": 3390
    },
    "standardDeviation": {
        "total": 2284,
        "ok": 0,
        "ko": 2284
    },
    "percentiles1": {
        "total": 2804,
        "ok": 0,
        "ko": 2804
    },
    "percentiles2": {
        "total": 5854,
        "ok": 0,
        "ko": 5854
    },
    "percentiles3": {
        "total": 6931,
        "ok": 0,
        "ko": 6931
    },
    "percentiles4": {
        "total": 7154,
        "ok": 0,
        "ko": 7154
    },
    "group1": {
        "name": "t < 500 ms",
        "count": 0,
        "percentage": 0
    },
    "group2": {
        "name": "500 ms < t < 1000 ms",
        "count": 0,
        "percentage": 0
    },
    "group3": {
        "name": "t > 1000 ms",
        "count": 0,
        "percentage": 0
    },
    "group4": {
        "name": "failed",
        "count": 1288,
        "percentage": 100
    },
    "meanNumberOfRequestsPerSecond": {
        "total": 7.0,
        "ok": 0,
        "ko": 7.0
    }
}
    },"req_get--api-v1-fro-08fa3": {
        "type": "REQUEST",
        "name": "GET /api/v1/front/trading/market/sell",
"path": "GET /api/v1/front/trading/market/sell",
"pathFormatted": "req_get--api-v1-fro-08fa3",
"stats": {
    "name": "GET /api/v1/front/trading/market/sell",
    "numberOfRequests": {
        "total": 1245,
        "ok": 0,
        "ko": 1245
    },
    "minResponseTime": {
        "total": 5,
        "ok": 0,
        "ko": 5
    },
    "maxResponseTime": {
        "total": 7354,
        "ok": 0,
        "ko": 7354
    },
    "meanResponseTime": {
        "total": 3266,
        "ok": 0,
        "ko": 3266
    },
    "standardDeviation": {
        "total": 2190,
        "ok": 0,
        "ko": 2190
    },
    "percentiles1": {
        "total": 2734,
        "ok": 0,
        "ko": 2734
    },
    "percentiles2": {
        "total": 5434,
        "ok": 0,
        "ko": 5434
    },
    "percentiles3": {
        "total": 6917,
        "ok": 0,
        "ko": 6917
    },
    "percentiles4": {
        "total": 7178,
        "ok": 0,
        "ko": 7178
    },
    "group1": {
        "name": "t < 500 ms",
        "count": 0,
        "percentage": 0
    },
    "group2": {
        "name": "500 ms < t < 1000 ms",
        "count": 0,
        "percentage": 0
    },
    "group3": {
        "name": "t > 1000 ms",
        "count": 0,
        "percentage": 0
    },
    "group4": {
        "name": "failed",
        "count": 1245,
        "percentage": 100
    },
    "meanNumberOfRequestsPerSecond": {
        "total": 6.766304347826087,
        "ok": 0,
        "ko": 6.766304347826087
    }
}
    },"req_get--api-v1-fro-47e53": {
        "type": "REQUEST",
        "name": "GET /api/v1/front/trading/limit/buy",
"path": "GET /api/v1/front/trading/limit/buy",
"pathFormatted": "req_get--api-v1-fro-47e53",
"stats": {
    "name": "GET /api/v1/front/trading/limit/buy",
    "numberOfRequests": {
        "total": 1266,
        "ok": 1189,
        "ko": 77
    },
    "minResponseTime": {
        "total": 6,
        "ok": 46,
        "ko": 6
    },
    "maxResponseTime": {
        "total": 20362,
        "ok": 20362,
        "ko": 375
    },
    "meanResponseTime": {
        "total": 10290,
        "ok": 10952,
        "ko": 76
    },
    "standardDeviation": {
        "total": 6665,
        "ok": 6333,
        "ko": 79
    },
    "percentiles1": {
        "total": 8286,
        "ok": 8707,
        "ko": 50
    },
    "percentiles2": {
        "total": 17752,
        "ok": 17970,
        "ko": 84
    },
    "percentiles3": {
        "total": 19999,
        "ok": 20014,
        "ko": 302
    },
    "percentiles4": {
        "total": 20215,
        "ok": 20221,
        "ko": 347
    },
    "group1": {
        "name": "t < 500 ms",
        "count": 24,
        "percentage": 2
    },
    "group2": {
        "name": "500 ms < t < 1000 ms",
        "count": 10,
        "percentage": 1
    },
    "group3": {
        "name": "t > 1000 ms",
        "count": 1155,
        "percentage": 91
    },
    "group4": {
        "name": "failed",
        "count": 77,
        "percentage": 6
    },
    "meanNumberOfRequestsPerSecond": {
        "total": 6.880434782608695,
        "ok": 6.461956521739131,
        "ko": 0.41847826086956524
    }
}
    },"req_get--api-v1-fro-8f516": {
        "type": "REQUEST",
        "name": "GET /api/v1/front/trading/limit/sell",
"path": "GET /api/v1/front/trading/limit/sell",
"pathFormatted": "req_get--api-v1-fro-8f516",
"stats": {
    "name": "GET /api/v1/front/trading/limit/sell",
    "numberOfRequests": {
        "total": 1222,
        "ok": 1174,
        "ko": 48
    },
    "minResponseTime": {
        "total": 6,
        "ok": 36,
        "ko": 6
    },
    "maxResponseTime": {
        "total": 20316,
        "ok": 20316,
        "ko": 178
    },
    "meanResponseTime": {
        "total": 10335,
        "ok": 10756,
        "ko": 52
    },
    "standardDeviation": {
        "total": 6503,
        "ok": 6286,
        "ko": 36
    },
    "percentiles1": {
        "total": 8291,
        "ok": 8584,
        "ko": 41
    },
    "percentiles2": {
        "total": 17787,
        "ok": 17958,
        "ko": 68
    },
    "percentiles3": {
        "total": 19988,
        "ok": 20005,
        "ko": 104
    },
    "percentiles4": {
        "total": 20209,
        "ok": 20210,
        "ko": 174
    },
    "group1": {
        "name": "t < 500 ms",
        "count": 17,
        "percentage": 1
    },
    "group2": {
        "name": "500 ms < t < 1000 ms",
        "count": 9,
        "percentage": 1
    },
    "group3": {
        "name": "t > 1000 ms",
        "count": 1148,
        "percentage": 94
    },
    "group4": {
        "name": "failed",
        "count": 48,
        "percentage": 4
    },
    "meanNumberOfRequestsPerSecond": {
        "total": 6.641304347826087,
        "ok": 6.380434782608695,
        "ko": 0.2608695652173913
    }
}
    }
}

}